<?xml version="1.0" encoding="utf-8" ?>
<dwsync>
<file name="Auth.php" server="hyperioninc.com/public_html/" local="128804436000000000" remote="128804436000000000" />
<file name="Auth.xml" server="hyperioninc.com/public_html/" local="128804436000000000" remote="128804436000000000" />
<file name="Build.php" server="hyperioninc.com/public_html/" local="128804436000000000" remote="128804436000000000" />
<file name="Build.xml" server="hyperioninc.com/public_html/" local="128804436000000000" remote="128804436000000000" />
<file name="Channels.php" server="hyperioninc.com/public_html/" local="128804436000000000" remote="128804436000000000" />
<file name="Channels.xml" server="hyperioninc.com/public_html/" local="128804436000000000" remote="128804436000000000" />
<file name="Common.php" server="hyperioninc.com/public_html/" local="128804436000000000" remote="128804436000000000" />
<file name="Config.php" server="hyperioninc.com/public_html/" local="128804436000000000" remote="128804436000000000" />
<file name="Config.xml" server="hyperioninc.com/public_html/" local="128804436000000000" remote="128804436000000000" />
<file name="Install.php" server="hyperioninc.com/public_html/" local="128804436000000000" remote="128804436000000000" />
<file name="Install.xml" server="hyperioninc.com/public_html/" local="128804436000000000" remote="128804436000000000" />
<file name="Mirror.php" server="hyperioninc.com/public_html/" local="128804436000000000" remote="128804436000000000" />
<file name="Mirror.xml" server="hyperioninc.com/public_html/" local="128804436000000000" remote="128804436000000000" />
<file name="Package.php" server="hyperioninc.com/public_html/" local="128804436000000000" remote="128804436000000000" />
<file name="Package.xml" server="hyperioninc.com/public_html/" local="128804436000000000" remote="128804436000000000" />
<file name="Pickle.php" server="hyperioninc.com/public_html/" local="128804436000000000" remote="128804436000000000" />
<file name="Pickle.xml" server="hyperioninc.com/public_html/" local="128804436000000000" remote="128804436000000000" />
<file name="Registry.php" server="hyperioninc.com/public_html/" local="128804436000000000" remote="128804436000000000" />
<file name="Registry.xml" server="hyperioninc.com/public_html/" local="128804436000000000" remote="128804436000000000" />
<file name="Remote.php" server="hyperioninc.com/public_html/" local="128804436000000000" remote="128804436000000000" />
<file name="Remote.xml" server="hyperioninc.com/public_html/" local="128804436000000000" remote="128804436000000000" />
<file name="Test.php" server="hyperioninc.com/public_html/" local="128804436000000000" remote="128804436000000000" />
<file name="Test.xml" server="hyperioninc.com/public_html/" local="128804436000000000" remote="128804436000000000" />
</dwsync>